usdm3/__info__.py
usdm3/__init__.py
usdm3/api/__init__.py
usdm3/api/activity.py
usdm3/api/address.py
usdm3/api/administration_duration.py
usdm3/api/agent_administration.py
usdm3/api/alias_code.py
usdm3/api/analysis_population.py
usdm3/api/api_base_model.py
usdm3/api/biomedical_concept.py
usdm3/api/biomedical_concept_category.py
usdm3/api/biomedical_concept_property.py
usdm3/api/biomedical_concept_surrogate.py
usdm3/api/characteristic.py
usdm3/api/code.py
usdm3/api/condition.py
usdm3/api/eligibility_criterion.py
usdm3/api/encounter.py
usdm3/api/endpoint.py
usdm3/api/estimand.py
usdm3/api/geographic_scope.py
usdm3/api/governance_date.py
usdm3/api/indication.py
usdm3/api/intercurrent_event.py
usdm3/api/masking.py
usdm3/api/narrative_content.py
usdm3/api/objective.py
usdm3/api/organization.py
usdm3/api/population_definition.py
usdm3/api/procedure.py
usdm3/api/quantity.py
usdm3/api/range.py
usdm3/api/response_code.py
usdm3/api/schedule_timeline.py
usdm3/api/schedule_timeline_exit.py
usdm3/api/scheduled_instance.py
usdm3/api/study.py
usdm3/api/study_amendment.py
usdm3/api/study_amendment_reason.py
usdm3/api/study_arm.py
usdm3/api/study_cell.py
usdm3/api/study_design.py
usdm3/api/study_element.py
usdm3/api/study_epoch.py
usdm3/api/study_identifier.py
usdm3/api/study_intervention.py
usdm3/api/study_protocol_document.py
usdm3/api/study_protocol_document_version.py
usdm3/api/study_site.py
usdm3/api/study_title.py
usdm3/api/study_version.py
usdm3/api/syntax_template.py
usdm3/api/syntax_template_dictionary.py
usdm3/api/timing.py
usdm3/api/transition_rule.py
usdm3/api/wrapper.py
usdm3/base/__init__.py
usdm3/base/api_instance.py
usdm3/base/id_manager.py
usdm3/base/singleton.py
usdm3/bc/__init__.py
usdm3/bc/cdisc/__init__.py
usdm3/bc/cdisc/bc_library.py
usdm3/bc/cdisc/library.py
usdm3/bc/cdisc/library_api.py
usdm3/bc/cdisc/library_cache/__init__.py
usdm3/bc/cdisc/library_cache/library_cache.py
usdm3/bc/cdisc/library_cache/library_cache.yaml
usdm3/ct/__init__.py
usdm3-0.12.1.dist-info/licenses/LICENSE
usdm3-0.12.1.dist-info/METADATA
usdm3-0.12.1.dist-info/WHEEL
usdm3-0.12.1.dist-info/top_level.txt
usdm3-0.12.1.dist-info/RECORD
