Metadata-Version: 2.4
Name: usdm3
Version: 0.12.1
Summary: A python package for using the CDISC TransCelerate USDM
Author: D Iberson-Hurst
Author-email: 
Classifier: Intended Audience :: Developers
Classifier: Programming Language :: Python
Classifier: Programming Language :: Python :: 3
Classifier: Programming Language :: Python :: 3.12
Classifier: Operating System :: OS Independent
License-File: LICENSE
Requires-Dist: pydantic==2.7.3
Requires-Dist: beautifulsoup4==4.12.3
Requires-Dist: pyyaml==6.0.1
Requires-Dist: simple_error_log>=0.6.0
Requires-Dist: jsonschema==4.23.0
Requires-Dist: python-dotenv==1.0.1
Requires-Dist: requests==2.32.3
Dynamic: author
Dynamic: classifier
Dynamic: description
Dynamic: description-content-type
Dynamic: license-file
Dynamic: requires-dist
Dynamic: summary
